SPINEX/SPINEX_Classifier.py
SPINEX/SPINEX_Regressor.py
SPINEX/__init__.py
SPINEX/data_preprocessor.py
SPINEX-0.2.dist-info/METADATA
SPINEX-0.2.dist-info/WHEEL
SPINEX-0.2.dist-info/top_level.txt
SPINEX-0.2.dist-info/RECORD
