Metadata-Version: 2.1
Name: SPINEX
Version: 0.2
Summary: A Python package for SPINEX algorithm
Home-page: https://arxiv.org/abs/2306.01029
License: UNKNOWN
Platform: UNKNOWN
Requires-Python: >=3.6
Requires-Dist: numpy
Requires-Dist: pandas
Requires-Dist: scikit-learn
Requires-Dist: scipy
